cogneed_protos/__init__.py
cogneed_protos/ai/__init__.py
cogneed_protos/ai/cogneed/__init__.py
cogneed_protos/ai/cogneed/api/__init__.py
cogneed_protos/ai/cogneed/api/common_pb2.py
cogneed_protos/ai/cogneed/api/common_pb2_grpc.py
cogneed_protos/ai/cogneed/api/audio/__init__.py
cogneed_protos/ai/cogneed/api/audio/common_pb2.py
cogneed_protos/ai/cogneed/api/audio/common_pb2_grpc.py
cogneed_protos/ai/cogneed/api/audio/web_middleware_pb2.py
cogneed_protos/ai/cogneed/api/audio/web_middleware_pb2_grpc.py
cogneed_protos/ai/cogneed/api/audio/detect/__init__.py
cogneed_protos/ai/cogneed/api/audio/detect/detect_pb2.py
cogneed_protos/ai/cogneed/api/audio/detect/detect_pb2_grpc.py
cogneed_protos/ai/cogneed/api/audio/recorder/__init__.py
cogneed_protos/ai/cogneed/api/audio/recorder/recorder_pb2.py
cogneed_protos/ai/cogneed/api/audio/recorder/recorder_pb2_grpc.py
cogneed_protos/ai/cogneed/api/audio/stream/__init__.py
cogneed_protos/ai/cogneed/api/audio/stream/audio_stream_pb2.py
cogneed_protos/ai/cogneed/api/audio/stream/audio_stream_pb2_grpc.py
cogneed_protos/ai/cogneed/api/contentmanagement/__init__.py
cogneed_protos/ai/cogneed/api/contentmanagement/content_management_pb2.py
cogneed_protos/ai/cogneed/api/contentmanagement/content_management_pb2_grpc.py
cogneed_protos/ai/cogneed/api/modelconfig/__init__.py
cogneed_protos/ai/cogneed/api/modelconfig/keyword_pb2.py
cogneed_protos/ai/cogneed/api/modelconfig/keyword_pb2_grpc.py
cogneed_protos/ai/cogneed/api/modelconfig/model_pb2.py
cogneed_protos/ai/cogneed/api/modelconfig/model_pb2_grpc.py
cogneed_protos/ai/cogneed/api/predict/__init__.py
cogneed_protos/ai/cogneed/api/predict/bulk/__init__.py
cogneed_protos/ai/cogneed/api/predict/bulk/bulk_prediction_pb2.py
cogneed_protos/ai/cogneed/api/predict/bulk/bulk_prediction_pb2_grpc.py
cogneed_protos/ai/cogneed/api/predict/eval/__init__.py
cogneed_protos/ai/cogneed/api/predict/eval/eval_prediction_pb2.py
cogneed_protos/ai/cogneed/api/predict/eval/eval_prediction_pb2_grpc.py
cogneed_protos-0.64.0.dist-info/METADATA
cogneed_protos-0.64.0.dist-info/WHEEL
cogneed_protos-0.64.0.dist-info/top_level.txt
cogneed_protos-0.64.0.dist-info/RECORD
